MANIFEST.in
README.md
requirements.txt
setup.py
src/npis_api_utils/__init__.py
src/npis_api_utils.egg-info/PKG-INFO
src/npis_api_utils.egg-info/SOURCES.txt
src/npis_api_utils.egg-info/dependency_links.txt
src/npis_api_utils.egg-info/not-zip-safe
src/npis_api_utils.egg-info/requires.txt
src/npis_api_utils.egg-info/top_level.txt
src/npis_api_utils/exceptions/__init__.py
src/npis_api_utils/schemas/__init__.py
src/npis_api_utils/schemas/formio_roles.py
src/npis_api_utils/services/__init__.py
src/npis_api_utils/services/external/__init__.py
src/npis_api_utils/services/external/formio.py
src/npis_api_utils/utils/__init__.py
src/npis_api_utils/utils/auth.py
src/npis_api_utils/utils/caching.py
src/npis_api_utils/utils/constants.py
src/npis_api_utils/utils/enums.py
src/npis_api_utils/utils/format.py
src/npis_api_utils/utils/logging.py
src/npis_api_utils/utils/pdf.py
src/npis_api_utils/utils/profiler.py
src/npis_api_utils/utils/roles.py
src/npis_api_utils/utils/startup.py
src/npis_api_utils/utils/user_context.py
src/npis_api_utils/utils/util.py
src/npis_api_utils/utils/translations/__init__.py
src/npis_api_utils/utils/translations/translations.py