Metadata-Version: 2.1
Name: npis-api-utils
Version: 1.0.0
Summary: NPIS api related libraries.
Home-page: https://github.com/katxeus/npis_api_utils
Author: JK
